pyqula/__init__.py
pyqula/algebra.py
pyqula/alloy.py
pyqula/angular.py
pyqula/bandfit.py
pyqula/bandstructure.py
pyqula/check.py
pyqula/checkclass.py
pyqula/chi.py
pyqula/classicalspin.py
pyqula/clean.py
pyqula/compilefortran.py
pyqula/convolution.py
pyqula/correlator.py
pyqula/crystalfield.py
pyqula/current.py
pyqula/data.py
pyqula/density.py
pyqula/densitymatrix.py
pyqula/diagonalize.py
pyqula/disorder.py
pyqula/disorder_heterostructure.py
pyqula/dos.py
pyqula/dyson.py
pyqula/effective.py
pyqula/embedding.py
pyqula/estimators.py
pyqula/extract.py
pyqula/fermisurface.py
pyqula/filesystem.py
pyqula/filling.py
pyqula/films.py
pyqula/fitting.py
pyqula/gap.py
pyqula/gauge.py
pyqula/geometry.py
pyqula/green.py
pyqula/groundstate.py
pyqula/gsenergy.py
pyqula/hall.py
pyqula/hamiltonians.py
pyqula/helptk.py
pyqula/heterostructures.py
pyqula/hexagonal.py
pyqula/hybrid.py
pyqula/increase_hilbert.py
pyqula/indexing.py
pyqula/inout.py
pyqula/integration.py
pyqula/interpolation.py
pyqula/ipr.py
pyqula/islands.py
pyqula/junctions.py
pyqula/kanemele.py
pyqula/kdos.py
pyqula/kdotp.py
pyqula/kekule.py
pyqula/keldysh.py
pyqula/klist.py
pyqula/kpm.py
pyqula/kwantlink.py
pyqula/latticegas.py
pyqula/ldos.py
pyqula/limits.py
pyqula/magneticexchange.py
pyqula/magnetism.py
pyqula/mass.py
pyqula/massive_green.py
pyqula/meanfield.py
pyqula/merge.py
pyqula/mullen.py
pyqula/multicell.py
pyqula/multihopping.py
pyqula/multilayers.py
pyqula/multiterminal.py
pyqula/neighbor.py
pyqula/nodes.py
pyqula/numbaneighbor.py
pyqula/old_chi.py
pyqula/operatorlist.py
pyqula/operators.py
pyqula/parallel.py
pyqula/parallelmaster.py
pyqula/parallelmpi.py
pyqula/parallelslurm.py
pyqula/peierls.py
pyqula/phasediagram.py
pyqula/potentials.py
pyqula/pseudocontact.py
pyqula/pyqula2dmrgpy.py
pyqula/randomtk.py
pyqula/rashba.py
pyqula/reciprocalmap.py
pyqula/reduce.py
pyqula/response.py
pyqula/ribbon.py
pyqula/ribbonizate.py
pyqula/rkky.py
pyqula/rotate_spin.py
pyqula/rpa.py
pyqula/sanitycheck.py
pyqula/scftypes.py
pyqula-0.0.89.dist-info/licenses/LICENSE.md
pyqula-0.0.89.dist-info/METADATA
pyqula-0.0.89.dist-info/WHEEL
pyqula-0.0.89.dist-info/top_level.txt
pyqula-0.0.89.dist-info/RECORD
