Metadata-Version: 2.4
Name: pyqula
Version: 0.0.89
Summary: Python library for quantum lattice tight binding models
Home-page: https://github.com/joselado/pyqula
Author: Jose Lado
Author-email: joselado@aalto.fi
Project-URL: Bug Tracker, https://github.com/joselado/pyqula/issues
Classifier: Programming Language :: Python :: 3
Classifier: Operating System :: OS Independent
Requires-Python: >=3.6
License-File: LICENSE.md
Requires-Dist: numba>=0.60.0
Requires-Dist: scipy
Requires-Dist: matplotlib
Requires-Dist: numpy
Dynamic: author
Dynamic: author-email
Dynamic: classifier
Dynamic: description
Dynamic: description-content-type
Dynamic: home-page
Dynamic: license-file
Dynamic: project-url
Dynamic: requires-dist
Dynamic: requires-python
Dynamic: summary
